README.md
setup.py
wildfire_evac/__init__.py
wildfire_evac.egg-info/PKG-INFO
wildfire_evac.egg-info/SOURCES.txt
wildfire_evac.egg-info/dependency_links.txt
wildfire_evac.egg-info/requires.txt
wildfire_evac.egg-info/top_level.txt
wildfire_evac/envs/__init__.py
wildfire_evac/envs/wildfire_evac.py
wildfire_evac/envs/environment/__init__.py
wildfire_evac/envs/environment/environment.py
wildfire_evac/envs/environment/environment_constant.py