Metadata-Version: 2.1
Name: wildfire-evac
Version: 0.0.14
Summary: An RL OpenAI Gym Environment for Wildfire Evacuation
Home-page: https://github.com/cpondoc/wildfire
Author: Celtics Big 3
Author-email: clpondoc@stanford.edu
License: UNKNOWN
Platform: UNKNOWN
Classifier: Programming Language :: Python :: 3
Classifier: License :: OSI Approved :: MIT License
Classifier: Operating System :: OS Independent
